theseus/__init__.py
theseus/_version.py
theseus/constants.py
theseus/global_params.py
theseus/py.typed
theseus/theseus_layer.py
theseus/core/__init__.py
theseus/core/cost_function.py
theseus/core/cost_weight.py
theseus/core/objective.py
theseus/core/robust_cost_function.py
theseus/core/robust_loss.py
theseus/core/theseus_function.py
theseus/core/variable.py
theseus/core/vectorizer.py
theseus/embodied/__init__.py
theseus/embodied/collision/__init__.py
theseus/embodied/collision/collision.py
theseus/embodied/collision/eff_obj_contact.py
theseus/embodied/collision/signed_distance_field.py
theseus/embodied/kinematics/__init__.py
theseus/embodied/kinematics/kinematics_model.py
theseus/embodied/measurements/__init__.py
theseus/embodied/measurements/between.py
theseus/embodied/measurements/moving_frame_between.py
theseus/embodied/measurements/reprojection.py
theseus/embodied/misc/__init__.py
theseus/embodied/misc/local_cost_fn.py
theseus/embodied/motionmodel/__init__.py
theseus/embodied/motionmodel/double_integrator.py
theseus/embodied/motionmodel/misc.py
theseus/embodied/motionmodel/quasi_static_pushing_planar.py
theseus/extlib/__init__.py
theseus/extlib/baspacho_solver.cpython-310-x86_64-linux-gnu.so
theseus/extlib/cusolver_lu_solver.cpython-310-x86_64-linux-gnu.so
theseus/extlib/mat_mult.cpython-310-x86_64-linux-gnu.so
theseus/geometry/__init__.py
theseus/geometry/lie_group.py
theseus/geometry/lie_group_check.py
theseus/geometry/manifold.py
theseus/geometry/point_types.py
theseus/geometry/se2.py
theseus/geometry/se3.py
theseus/geometry/so2.py
theseus/geometry/so3.py
theseus/geometry/utils.py
theseus/geometry/vector.py
theseus/optimizer/__init__.py
theseus/optimizer/dense_linearization.py
theseus/optimizer/linear_system.py
theseus/optimizer/linearization.py
theseus/optimizer/manifold_gaussian.py
theseus/optimizer/optimizer.py
theseus/optimizer/sparse_linearization.py
theseus/optimizer/variable_ordering.py
theseus/optimizer/autograd/__init__.py
theseus_ai-0.2.2.dist-info/LICENSE
theseus_ai-0.2.2.dist-info/METADATA
theseus_ai-0.2.2.dist-info/WHEEL
theseus_ai-0.2.2.dist-info/top_level.txt
theseus_ai-0.2.2.dist-info/RECORD
